cdk_image_moderation/__init__.py
cdk_image_moderation/py.typed
cdk_image_moderation/_jsii/__init__.py
cdk_image_moderation/_jsii/cdk-image-moderation@0.1.193.jsii.tgz
cdk_image_moderation-0.1.193.dist-info/LICENSE
cdk_image_moderation-0.1.193.dist-info/METADATA
cdk_image_moderation-0.1.193.dist-info/WHEEL
cdk_image_moderation-0.1.193.dist-info/top_level.txt
cdk_image_moderation-0.1.193.dist-info/RECORD
